LICENSE
MANIFEST.in
README.md
requirements.txt
setup.cfg
setup.py
ultralytics/__init__.py
ultralytics/detect.py
ultralytics/train.py
ultralytics/val.py
ultralytics/hub/__init__.py
ultralytics/hub/auth.py
ultralytics/hub/config.py
ultralytics/hub/session.py
ultralytics/hub/utils.py
ultralytics/nn/__init__.py
ultralytics/nn/autobackend.py
ultralytics/nn/modules.py
ultralytics/nn/tasks.py
ultralytics/utils/__init__.py
ultralytics/utils/activations.py
ultralytics/utils/augmentations.py
ultralytics/utils/autoanchor.py
ultralytics/utils/autobatch.py
ultralytics/utils/callbacks.py
ultralytics/utils/dataloaders.py
ultralytics/utils/downloads.py
ultralytics/utils/general.py
ultralytics/utils/loss.py
ultralytics/utils/metrics.py
ultralytics/utils/plots.py
ultralytics/utils/torch_utils.py
ultralytics/utils/triton.py
ultralytics/utils/aws/__init__.py
ultralytics/utils/aws/resume.py
ultralytics/utils/loggers/__init__.py
ultralytics/utils/loggers/clearml/__init__.py
ultralytics/utils/loggers/clearml/clearml_utils.py
ultralytics/utils/loggers/clearml/hpo.py
ultralytics/utils/loggers/comet/__init__.py
ultralytics/utils/loggers/comet/comet_utils.py
ultralytics/utils/loggers/comet/hpo.py
ultralytics/utils/loggers/wandb/__init__.py
ultralytics/utils/loggers/wandb/log_dataset.py
ultralytics/utils/loggers/wandb/sweep.py
ultralytics/utils/loggers/wandb/wandb_utils.py
ultralytics/utils/segment/__init__.py
ultralytics/utils/segment/augmentations.py
ultralytics/utils/segment/dataloaders.py
ultralytics/utils/segment/general.py
ultralytics/utils/segment/loss.py
ultralytics/utils/segment/metrics.py
ultralytics/utils/segment/plots.py
ultralytics/yolo/__init__.py
ultralytics/yolo/cli.py
ultralytics/yolo/configs/__init__.py
ultralytics/yolo/configs/hydra_patch.py
ultralytics/yolo/data/__init__.py
ultralytics/yolo/data/augment.py
ultralytics/yolo/data/base.py
ultralytics/yolo/data/build.py
ultralytics/yolo/data/dataset.py
ultralytics/yolo/data/dataset_wrappers.py
ultralytics/yolo/data/utils.py
ultralytics_yolov8.egg-info/PKG-INFO
ultralytics_yolov8.egg-info/SOURCES.txt
ultralytics_yolov8.egg-info/dependency_links.txt
ultralytics_yolov8.egg-info/requires.txt
ultralytics_yolov8.egg-info/top_level.txt